llmabstractions/__init__.py
llmabstractions/exceptions.py
llmabstractions/parsers/__init__.py
llmabstractions/parsers/json_response.py
llmabstractions-0.0.1.dist-info/LICENSE
llmabstractions-0.0.1.dist-info/METADATA
llmabstractions-0.0.1.dist-info/WHEEL
llmabstractions-0.0.1.dist-info/top_level.txt
llmabstractions-0.0.1.dist-info/RECORD
