Metadata-Version: 2.1
Name: llmabstractions
Version: 0.0.1
Summary: A Python library abstracting the way you interact with LLMs.
Author-email: Kostas Tsolis <kostas.tsolis@dialectos.ai>
License: MIT License
Project-URL: homepage, https://github.com/dialectos-ai/llmabstractions
Project-URL: documentation, https://llmabstractions.readthedocs.io/en/latest/index.html
Project-URL: repository, https://github.com/dialectos-ai/llmabstractions
Requires-Python: >=3.9
License-File: LICENSE
